ace_of_clust/__init__.py
ace_of_clust/analysis.py
ace_of_clust/io.py
ace_of_clust/plot.py
ace_of_clust/resources/default_colors.txt
ace_of_clust/resources/distruct_colors.txt
ace_of_clust/wrappers.py
ace_of_clust-0.1.3.dist-info/LICENSE
ace_of_clust-0.1.3.dist-info/METADATA
ace_of_clust-0.1.3.dist-info/WHEEL
ace_of_clust-0.1.3.dist-info/RECORD
