Metadata-Version: 2.1
Name: ace-of-clust
Version: 0.1.3
Summary: ACE-OF-Clust: Alignment, Comparison, and Evaluation of Omics Features in Clustering
Home-page: https://github.com/xr-cc/ace-of-clust
License: MIT
Author: Xiran Liu
Author-email: xiran_liu1@brown.edu
Requires-Python: >=3.9,<3.12
Classifier: License :: OSI Approved :: MIT License
Classifier: Programming Language :: Python :: 3
Classifier: Programming Language :: Python :: 3.9
Classifier: Programming Language :: Python :: 3.10
Classifier: Programming Language :: Python :: 3.11
Provides-Extra: adjusttext
Requires-Dist: adjustText (>=0.8) ; extra == "adjusttext"
Requires-Dist: clumppling (>=2.0)
Requires-Dist: matplotlib (>=3.5)
Requires-Dist: numpy (>=1.21)
Requires-Dist: pandas (>=1.5)
Requires-Dist: seaborn (>=0.12)
Project-URL: Documentation, https://xr-cc.github.io/ace-of-clust/
Project-URL: Repository, https://github.com/xr-cc/ace-of-clust
